tornado_prof
