Metadata-Version: 1.1
Name: tornado-prof
Version: 0.0.6
Summary: Tornado Profiling Library
Home-page: https://github.com/jacksontj/tornado-prof
Author: Thomas Jackson
Author-email: jacksontj.89@gmail.com
License: MIT
Platform: UNKNOWN
Classifier: Development Status :: 3 - Alpha
Classifier: License :: OSI Approved :: MIT License
Classifier: Programming Language :: Python :: 2.7
